create_flask_package/__init__.py
create_flask_package/create_flask_package.py
create_flask_package-0.1.6.dist-info/METADATA
create_flask_package-0.1.6.dist-info/WHEEL
create_flask_package-0.1.6.dist-info/entry_points.txt
create_flask_package-0.1.6.dist-info/top_level.txt
create_flask_package-0.1.6.dist-info/RECORD
