Metadata-Version: 2.1
Name: create_flask_package
Version: 0.1.6
Summary: A CLI tool for generating Flask web application scaffolding.
Home-page: https://github.com/dev-nasir-iqbal/create_flask_package
Author: Nasir Iqbal
License: MIT
Requires-Dist: Flask
Requires-Dist: Flask-SQLAlchemy
Requires-Dist: Flask-CORS
Requires-Dist: Flask-Login
Requires-Dist: Flask-Session
